[
  {
    "inputs": [
      {
        "internalType": "address",
        "name": "_factory",
        "type": "address"
      },
      {
        "internalType": "address",
        "name": "_formula",
        "type": "address"
      },
      {
        "internalType": "address",
        "name": "_WETH",
        "type": "address"
      }
    ],
    "stateMutability": "nonpayable",
    "type": "constructor"
  },
  {
    "anonymous": false,
    "inputs": [
      {
        "indexed": false,
        "internalType": "address",
        "name": "pair",
        "type": "address"
      },
      {
        "indexed": false,
        "internalType": "uint256",
        "name": "amountOut",
        "type": "uint256"
      },
      {
        "indexed": false,
        "internalType": "address",
        "name": "output",
        "type": "address"
      }
    ],
    "name": "Exchange",
    "type": "event"
  },
  {
    "anonymous": false,
    "inputs": [
      {
        "indexed": true,
        "internalType": "address",
        "name": "previousOwner",
        "type": "address"
      },
      {
        "indexed": true,
        "internalType": "address",
        "name": "newOwner",
        "type": "address"
      }
    ],
    "name": "OwnershipTransferred",
    "type": "event"
  },
  {
    "inputs": [],
    "name": "WETH",
    "outputs": [
      {
        "internalType": "address",
        "name": "",
        "type": "address"
      }
    ],
    "stateMutability": "view",
    "type": "function"
  },
  {
    "inputs": [
      {
        "internalType": "bytes",
        "name": "data",
        "type": "bytes"
      }
    ],
    "name": "callBytes",
    "outputs": [],
    "stateMutability": "payable",
    "type": "function"
  },
  {
    "inputs": [],
    "name": "factory",
    "outputs": [
      {
        "internalType": "address",
        "name": "",
        "type": "address"
      }
    ],
    "stateMutability": "view",
    "type": "function"
  },
  {
    "inputs": [],
    "name": "formula",
    "outputs": [
      {
        "internalType": "address",
        "name": "",
        "type": "address"
      }
    ],
    "stateMutability": "view",
    "type": "function"
  },
  {
    "inputs": [
      {
        "components": [
          {
            "internalType": "bytes",
            "name": "data",
            "type": "bytes"
          },
          {
            "internalType": "uint16",
            "name": "dexOption",
            "type": "uint16"
          }
        ],
        "internalType": "struct IMultihopRouter.Swap[][]",
        "name": "swapSequences",
        "type": "tuple[][]"
      },
      {
        "internalType": "address",
        "name": "tokenIn",
        "type": "address"
      },
      {
        "internalType": "address",
        "name": "tokenOut",
        "type": "address"
      },
      {
        "internalType": "uint256",
        "name": "minTotalAmountOut",
        "type": "uint256"
      },
      {
        "internalType": "address",
        "name": "to",
        "type": "address"
      },
      {
        "internalType": "uint256",
        "name": "deadline",
        "type": "uint256"
      },
      {
        "internalType": "bytes",
        "name": "destTokenFeeData",
        "type": "bytes"
      }
    ],
    "name": "multihopBatchSwapExactIn",
    "outputs": [
      {
        "internalType": "uint256",
        "name": "totalAmountOut",
        "type": "uint256"
      }
    ],
    "stateMutability": "payable",
    "type": "function"
  },
  {
    "inputs": [],
    "name": "owner",
    "outputs": [
      {
        "internalType": "address",
        "name": "",
        "type": "address"
      }
    ],
    "stateMutability": "view",
    "type": "function"
  },
  {
    "inputs": [],
    "name": "renounceOwnership",
    "outputs": [],
    "stateMutability": "nonpayable",
    "type": "function"
  },
  {
    "inputs": [
      {
        "internalType": "address",
        "name": "token",
        "type": "address"
      },
      {
        "internalType": "uint256",
        "name": "amount",
        "type": "uint256"
      }
    ],
    "name": "rescueFunds",
    "outputs": [],
    "stateMutability": "nonpayable",
    "type": "function"
  },
  {
    "inputs": [
      {
        "internalType": "address",
        "name": "newOwner",
        "type": "address"
      }
    ],
    "name": "transferOwnership",
    "outputs": [],
    "stateMutability": "nonpayable",
    "type": "function"
  },
  {
    "inputs": [
      {
        "internalType": "int256",
        "name": "amount0Delta",
        "type": "int256"
      },
      {
        "internalType": "int256",
        "name": "amount1Delta",
        "type": "int256"
      },
      {
        "internalType": "bytes",
        "name": "_data",
        "type": "bytes"
      }
    ],
    "name": "uniswapV3SwapCallback",
    "outputs": [],
    "stateMutability": "nonpayable",
    "type": "function"
  },
  {
    "stateMutability": "payable",
    "type": "receive"
  }
]